setup.py
visualproxy/__init__.py
visualproxy/adapter.py
visualproxy/interfaces.py
visualproxy/proxy.py
visualproxy/reflect.py
visualproxy.egg-info/PKG-INFO
visualproxy.egg-info/SOURCES.txt
visualproxy.egg-info/dependency_links.txt
visualproxy.egg-info/requires.txt
visualproxy.egg-info/top_level.txt
visualproxy/gtkui/__init__.py
visualproxy/gtkui/gtkview.py
visualproxy/gtkui/interfaces.py
visualproxy/gtkui/signal.py
visualproxy/gtkui/signalbroker.py
visualproxy/gtkui/widgets.py
