Metadata-Version: 1.0
Name: visualproxy
Version: 0.1
Summary: VisualProxy for Python
Home-page: http://code.launchpad.net/visualproxy/
Author: Johan Dahlin
Author-email: jdahlin@async.com.br
License: GPL
Keywords: visualproxy proxy mvc user interface pygtk gtk
Platform: UNKNOWN
